.VERSION
AUTHORS.rst
CONTRIBUTING.rst
HISTORY.rst
LICENSE
MANIFEST.in
Pipfile
Pipfile.lock
README.rst
USAGE.rst
dev-requirements.txt
requirements.txt
setup.cfg
setup.py
docs/Makefile
docs/authors.rst
docs/conf.py
docs/contributing.rst
docs/enpassreaderlib.rst
docs/history.rst
docs/index.rst
docs/installation.rst
docs/modules.rst
docs/readme.rst
docs/usage.rst
enpassreaderlib/.VERSION
enpassreaderlib/AUTHORS.rst
enpassreaderlib/CONTRIBUTING.rst
enpassreaderlib/HISTORY.rst
enpassreaderlib/LICENSE
enpassreaderlib/Pipfile
enpassreaderlib/Pipfile.lock
enpassreaderlib/README.rst
enpassreaderlib/USAGE.rst
enpassreaderlib/__init__.py
enpassreaderlib/_version.py
enpassreaderlib/dev-requirements.txt
enpassreaderlib/enpassreaderlib.py
enpassreaderlib/enpassreaderlibexceptions.py
enpassreaderlib/requirements.txt
enpassreaderlib.egg-info/PKG-INFO
enpassreaderlib.egg-info/SOURCES.txt
enpassreaderlib.egg-info/dependency_links.txt
enpassreaderlib.egg-info/not-zip-safe
enpassreaderlib.egg-info/requires.txt
enpassreaderlib.egg-info/top_level.txt
enpassreaderlib/__pycache__/__init__.cpython-39.pyc
enpassreaderlib/__pycache__/_version.cpython-39.pyc
enpassreaderlib/__pycache__/enpassreaderlib.cpython-39.pyc
enpassreaderlib/__pycache__/enpassreaderlibexceptions.cpython-39.pyc
tests/test_enpassreaderlib.py