Metadata-Version: 2.4
Name: enpassreaderlib
Version: 0.2.6
Summary: A library implementing the decrypting and retrieving secrets from an enpass 6 database.
Home-page: https://github.com/costastf/enpassreaderlib
Author: Costas Tyfoxylos
Author-email: costas.tyf@gmail.com
License: MIT
Keywords: enpassreaderlib enpass 6
Classifier: Development Status :: 4 - Beta
Classifier: Intended Audience :: Developers
Classifier: License :: OSI Approved :: MIT License
Classifier: Natural Language :: English
Classifier: Programming Language :: Python :: 3.7
License-File: LICENSE
License-File: AUTHORS.rst
Requires-Dist: pysqlcipher3>=1.2.0; python_version >= "3.3"
Requires-Dist: pycryptodome>=3.23.0; python_version >= "2.7" and python_version not in "3.0, 3.1, 3.2, 3.3, 3.4, 3.5, 3.6"
Dynamic: author
Dynamic: author-email
Dynamic: classifier
Dynamic: description
Dynamic: home-page
Dynamic: keywords
Dynamic: license
Dynamic: license-file
Dynamic: requires-dist
Dynamic: summary
